d3shims.py
d3shims-0.1.1.dist-info/top_level.txt
d3shims-0.1.1.dist-info/METADATA
d3shims-0.1.1.dist-info/DESCRIPTION.rst
d3shims-0.1.1.dist-info/metadata.json
d3shims-0.1.1.dist-info/WHEEL
d3shims-0.1.1.dist-info/RECORD
