Metadata-Version: 2.0
Name: d3shims
Version: 0.1.1
Summary: Shim functions to generate D3 plots
Home-page: https://github.com/nicktimko/d3shims
Author: Nick Timkovich
Author-email: npt@u.northwestern.edu
License: MIT
